PFL/__init__.py
PFL/_version.py
PFL/exception.py
PFL/version.py
PFL/file/csv.py
PFL/file/file.py
PFL/file/txt.py
PythonFileLib-0.0.3.dist-info/LICENSE
PythonFileLib-0.0.3.dist-info/METADATA
PythonFileLib-0.0.3.dist-info/WHEEL
PythonFileLib-0.0.3.dist-info/top_level.txt
PythonFileLib-0.0.3.dist-info/RECORD
