Metadata-Version: 2.1
Name: PythonFileLib
Version: 0.0.3
Summary: The file processing collection for Python
Author: Sky Yang
Author-email: skyprotecter0911@foxmail.com
Platform: Linux
Platform: Windows
Platform: MacOS
Classifier: Programming Language :: Python :: 3
Classifier: Programming Language :: Python :: 3.7
Classifier: Programming Language :: Python :: 3.8
Classifier: Programming Language :: Python :: 3.9
Classifier: Programming Language :: Python :: 3.10
Classifier: Programming Language :: Python :: 3.11
Classifier: Programming Language :: Python :: 3.12
Classifier: Programming Language :: Python :: 3.13
Classifier: License :: OSI Approved :: MIT License
Classifier: Operating System :: OS Independent
Requires-Python: >=3.7
License-File: LICENSE
Requires-Dist: numpy >=2.0.0
Requires-Dist: pandas >=1.22.0
Requires-Dist: setuptools >=61.0
